icepy/basic.py
icepy/config.py
icepy/database.py
icepy/modeleditor.py
icepy/readhtml.py
icepy/runscript.py
icepy/simulation.py
icepy/util.py
icepy/wwr.py
icepy/zoneclone.py
icepy/zonestructure/__init__.py
icepy/zonestructure/doorstrc.py
icepy/zonestructure/thermbdg.py
icepy/zonestructure/winstrc.py
icepy/zonestructure/zonestrc.py
icepy2/basic.py
icepy2/config.py
icepy2/database.py
icepy2/modeleditor.py
icepy2/readhtml.py
icepy2/runscript.py
icepy2/simulation.py
icepy2/util.py
icepy2/wwr.py
icepy2/zoneclone.py
icepy-0.0.7.dist-info/METADATA
icepy-0.0.7.dist-info/WHEEL
icepy-0.0.7.dist-info/entry_points.txt
icepy-0.0.7.dist-info/top_level.txt
icepy-0.0.7.dist-info/RECORD
