Metadata-Version: 2.1
Name: icepy
Version: 0.0.7
Summary: Automated simulation tool for IDA ICE
Home-page: https://github.com/chenglongfu11/icepy
Author: Clong
Author-email: fuc369702700@gmail.com
License: MIT Licence
Platform: any
Classifier: Programming Language :: Python :: 3
Requires-Dist: pandas
Requires-Dist: plotly
Requires-Dist: pymysql
Requires-Dist: beautifulsoup4
Requires-Dist: numpy
